setup.py
django_typogrify.egg-info/PKG-INFO
django_typogrify.egg-info/SOURCES.txt
django_typogrify.egg-info/dependency_links.txt
django_typogrify.egg-info/pbr.json
django_typogrify.egg-info/requires.txt
django_typogrify.egg-info/top_level.txt
typogrify/__init__.py
typogrify/titlecase.py
typogrify/templatetags/__init__.py
typogrify/templatetags/typogrify_tags.py