Metadata-Version: 1.1
Name: django-typogrify
Version: 1.3.3
Summary: Make type not look like crap (for django apps)
Home-page: http://github.com/chrisdrackett/django-typogrify
Author: Chris Drackett
Author-email: chris@tiltshiftstudio.com
License: UNKNOWN
Platform: UNKNOWN
Classifier: Development Status :: 5 - Production/Stable
Classifier: Environment :: Web Environment
Classifier: Intended Audience :: Developers
Classifier: Natural Language :: English
Classifier: License :: OSI Approved :: BSD License
Classifier: Operating System :: OS Independent
Classifier: Programming Language :: Python
Classifier: Framework :: Django
Classifier: Topic :: Utilities
Classifier: Topic :: Text Processing
